dimgnet/__init__.py
dimgnet/bar.py
dimgnet/download_img.py
dimgnet/progress.py
dimgnet-0.0.2.dist-info/LICENSE
dimgnet-0.0.2.dist-info/METADATA
dimgnet-0.0.2.dist-info/WHEEL
dimgnet-0.0.2.dist-info/entry_points.txt
dimgnet-0.0.2.dist-info/top_level.txt
dimgnet-0.0.2.dist-info/RECORD
