Metadata-Version: 2.1
Name: dimgnet
Version: 0.0.2
Summary: download imagenet package
Home-page: UNKNOWN
Author: Mai Tu Duy
Author-email: maituduy1998@gmail.com
License: UNKNOWN
Platform: UNKNOWN
Classifier: Programming Language :: Python :: 3
Classifier: License :: OSI Approved :: MIT License
Classifier: Operating System :: OS Independent
